defenitions.v

`define OPCODE_OP       7'b0110011
`define OPCODE_OP_IMM   7'b0010011
`define OPCODE_BRANCH   7'b1100011

`define FUNCT3_ADDSUB   3'b000
`define FUNCT3_SLL      3'b001
`define FUNCT3_SLT      3'b010
`define FUNCT3_SLTU     3'b011
`define FUNCT3_XOR      3'b100
`define FUNCT3_SRLA     3'b101
`define FUNCT3_OR       3'b110
`define FUNCT3_AND      3'b111

instr_exec.v

`include "defenitions.v"

module instr_exec(
    input clk,
    input rst,
    input [6:0] opcode,
    input [2:0] funct3,
    input [6:0] funct7,
    input [31:0] op1,
    input [31:0] op2,
    input [12:0] offset,
    input [31:0] pc,
    input [4:0] rd,
    output reg [4:0] reg_addr,
    output reg [31:0] reg_data,
    output reg [31:0] mem_addr,
    output reg mem_ren,
    output reg mem_wen
);

always @ (posedge clk, posedge rst)
if (rst) begin
    reg_addr <= 0;
end
else if (clk) begin
    case (opcode)
    0: begin
        mem_wen <= 0;
        mem_ren <= 0;
        reg_addr <= 0;
    end
    `OPCODE_OP, `OPCODE_OP_IMM: begin
        reg_addr <= rd;
        case (funct3)
        `FUNCT3_ADDSUB:
            if (!funct7) reg_data <= op1 + op2; // ADD
            else reg_data <= op1 + ~op2 + 1'b1; // SUB
        `FUNCT3_SLL: reg_data <= op1 << op2[4:0];
        `FUNCT3_SLT: reg_data <= ($signed(op1) < $signed(op2)) ? 1 : 0;
        `FUNCT3_SLTU: reg_data <= (op1 < op2) ? 1 : 0;
        `FUNCT3_XOR: reg_data <= op1 ^ op2;
        `FUNCT3_SRLA:
            if (!funct7) reg_data <= op1 >> op2[4:0]; // SRL
            else reg_data <= op1 >>> op2[4:0]; // SRA
        `FUNCT3_OR: reg_data <= op1 | op2;
        `FUNCT3_AND: reg_data <= op1 & op2;
        endcase
    end
    endcase
end

endmodule

src/instr_decode.v

`include "defenitions.v"

module instr_decode(
    input rst,
    input clk,
    input [31:0] ir_in,
    input [31:0] r1_data,
    input [31:0] r2_data,
    output reg [4:0] r1_addr,
    output reg [4:0] r2_addr,
    output wire [4:0] rd,
    output reg [31:0] op1,
    output reg [31:0] op2,
    output reg [12:0] offset,
    output wire [6:0] opcode,
    output wire [2:0] funct3,
    output wire [6:0] funct7
);

reg [31:0] ir;
wire rs1, rs2;

assign opcode = ir[6:0];
assign rs1 = ir[19:15];
assign rs2 = ir[24:20];
assign rd = ir[11:7];
assign funct3 = ir[14:12];
assign funct7 = ir[31:25];

always @ (posedge clk, posedge rst)
if (rst) ir <= 0;
else if (clk) ir <= ir_in;

always @ (*)
begin
    case (opcode)
    0: begin
        op1 <= 0;
        op2 <= 0;
        offset <= 0;
    end
    `OPCODE_OP: begin
        r1_addr <= rs1;
        op1 <= r1_data;
        r2_addr <= rs2;
        op2 <= r2_data;
    end
    `OPCODE_OP_IMM: begin
        r1_addr <= rs1;
        op1 <= r1_data;
        if (funct3 == `FUNCT3_SLL || funct3 == `FUNCT3_SRLA)
            op2 <= ir[24:20];
        else
            op2 <= { {20{ir[31]}}, ir[31:20] };
    end
    `OPCODE_BRANCH: begin
        r1_addr <= rs1;
        op1 <= r1_data;
        r2_addr <= rs2;
        op2 <= r2_data;
        offset <= { {20{ir[31]}}, ir[11], ir[30:25], ir[11:8], 1'b0 };
    end
    endcase
end

endmodule

instr_fetch.v

module instr_fetch(
    input rst,
    input clk,
    input pc_set,
    input [31:0] pc_data,
    input [31:0] mem_data,
    output reg [31:0] mem_addr,
    output wire [31:0] ir,
    output reg [31:0] pc
);

assign ir = mem_data;

always @ (posedge clk, posedge rst)
begin
    if (rst) pc = 0;
    else if (clk)
    begin
        if (pc_set)
        begin
            mem_addr <= pc_data;
            pc <= pc_data + 4;
        end
        else
        begin
            mem_addr <= pc;
            pc <= pc + 4;
        end
    end
end

endmodule

registers.v

module registers (
    input rst,
    input clk,
    input [4:0] r1_addr,
    input [4:0] r2_addr,
    input [4:0] rd1_addr, // Write back from exec
    input [4:0] rd2_addr, // Write back from mem
    input [31:0] rd1_data,
    input [31:0] rd2_data,
    output reg [31:0]  r1_data,
    output reg [31:0]  r2_data
);

reg [31:0] r [0:31];

always @ (r1_addr, rd2_addr, rd2_data, rd1_addr, rd1_data)
    if (r1_addr == 0) r1_data <= 0;
    else if (r1_addr == rd2_addr) r1_data <= rd2_data;
    else if (r1_addr == rd1_addr) r1_data <= rd1_data;
    else r1_data <= r[r1_addr];

always @ (r2_addr, rd2_addr, rd2_data, rd1_addr, rd1_data)
    if (r2_addr == 0) r2_data <= 0;
    else if (r2_addr == rd2_addr) r2_data <= rd2_data;
    else if (r2_addr == rd1_addr) r2_data <= rd1_data;
    else r2_data <= r[r2_addr];

reg [6:0] i;
always @ (posedge clk, posedge rst)
if (rst)
    for (i = 0; i < 32; i++) r[i] <= 0;
else if (clk) begin
    if (rd1_addr) r[rd1_addr] <= rd1_data;
    if (rd2_addr) r[rd2_addr] <= rd2_data;
end

endmodule

cpu.v

`define STATE_NONE 3'b000
`define STATE_FETCH 3'b001
`define STATE_DECODE 3'b010
`define STATE_EXEC 3'b011

module cpu(
    input [31:0] data_in,
    input rst,
    input clk,
    output wire [31:0] addr,
    output wire [31:0] data_out,
    output wire mem_ren,
    output wire mem_wen
);

wire fetch;
wire decode;
wire execute;
reg [2:0] state;
reg [2:0] next_state;

wire [31:0] fetch_ir, fetch_pc;

wire [4:0] r1_addr, r2_addr, rd1_addr, rd2_addr, decode_rd;
wire [31:0] r1_data, r2_data, rd1_data, rd2_data, decode_op1, decode_op2;
wire [12:0] decode_offset;
wire [6:0] decode_opcode, decode_funct7;
wire [2:0] decode_funct3;

assign fetch = state == `STATE_FETCH;
assign decode = state == `STATE_DECODE;
assign execute = state == `STATE_EXEC;

assign mem_ren = fetch;
assign mem_wen = 1'b0;
assign data_out = 0;

always @ (posedge clk, posedge rst)
    if (rst) state <= `STATE_NONE;
    else if (clk) state <= next_state;

always @ (*)
    case (state)
    `STATE_FETCH: next_state <= `STATE_DECODE;
    `STATE_DECODE: next_state <= `STATE_EXEC;
    `STATE_EXEC: next_state <= `STATE_FETCH;
    default: next_state <= `STATE_FETCH;
    endcase

registers registers (
    .rst(rst),
    .clk(clk),
    .r1_addr(r1_addr),
    .r2_addr(r2_addr),
    .rd1_addr(rd1_addr),
    .rd2_addr(rd2_addr),
    .rd1_data(rd1_data),
    .rd2_data(rd2_data),
    .r1_data(r1_data),
    .r2_data(r2_data)
);

instr_fetch instr_fetch (
    .clk(fetch),
    .rst(rst),
    .pc_set(1'b0),
    .pc_data(32'b0),
    .mem_data(data_in),
    .mem_addr(addr),
    .ir(fetch_ir),
    .pc(fetch_pc)
);

instr_decode instr_decode (
    .clk(decode),
    .rst(rst),
    .ir_in(fetch_ir),
    .r1_data(r1_data),
    .r2_data(r2_data),
    .r1_addr(r1_addr),
    .r2_addr(r2_addr),
    .rd(decode_rd),
    .op1(decode_op1),
    .op2(decode_op2),
    .offset(decode_offset),
    .opcode(decode_opcode),
    .funct3(decode_funct3),
    .funct7(decode_funct7)
);

instr_exec instr_exec (
    .clk(execute),
    .rst(rst),
    .opcode(decode_opcode),
    .funct3(decode_funct3),
    .funct7(decode_funct7),
    .op1(decode_op1),
    .op2(decode_op2),
    .offset(decode_offset),
    .pc(fetch_pc),
    .rd(decode_rd),
    .reg_addr(rd1_addr),
    .reg_data(rd1_data)
);

endmodule

src/memory.v

module memory(
    input clk,
    input [31:0] data_in,
    input [31:0] addr,
    input mem_ren,
    input mem_wen,
    output reg [31:0] data_out
);

reg [7:0] m [0:1023];

always @ (mem_ren, addr)
    if (mem_ren) data_out <= { m[addr + 3], m[addr + 2], m[addr + 1], m[addr] };

endmodule

src/cpu_tb.v

module cpu_tb ();

wire [31:0] mem_data_in;
wire [31:0] mem_addr;
wire mem_ren;
wire mem_wen;
wire [31:0] mem_data_out;

reg clk;
reg rst;
initial clk = 0;
always #50 clk = !clk;

initial begin
    rst = 1;
    #75 rst = 0;
end

memory mem (
    .clk(clk),
    .data_in(mem_data_in),
    .addr(mem_addr),
    .mem_ren(mem_ren),
    .mem_wen(mem_wen),
    .data_out(mem_data_out)
);

cpu cpu (
    .data_in(mem_data_out),
    .rst(rst),
    .clk(clk),
    .addr(mem_addr),
    .data_out(mem_data_in),
    .mem_ren(mem_ren),
    .mem_wen(mem_wen)
);

initial begin
    $readmemh("source_files/test1.hex", mem.m);
    $dumpfile("cpu_tb.vcd");
    $dumpvars;
    #1000 $finish;
end

endmodule

cpu_tb.vcd
$date
	Sat Dec 19 20:10:26 2020
$end
$version
	Icarus Verilog
$end
$timescale
	1s
$end
$scope module cpu_tb $end
$var wire 32 ! mem_data_in [31:0] $end
$var wire 1 " mem_wen $end
$var wire 1 # mem_ren $end
$var wire 32 $ mem_data_out [31:0] $end
$var wire 32 % mem_addr [31:0] $end
$var reg 1 & clk $end
$var reg 1 ' rst $end
$scope module cpu $end
$var wire 1 & clk $end
$var wire 32 ( data_out [31:0] $end
$var wire 1 # mem_ren $end
$var wire 1 " mem_wen $end
$var wire 5 ) rd2_addr [4:0] $end
$var wire 32 * rd2_data [31:0] $end
$var wire 1 ' rst $end
$var wire 32 + rd1_data [31:0] $end
$var wire 5 , rd1_addr [4:0] $end
$var wire 32 - r2_data [31:0] $end
$var wire 5 . r2_addr [4:0] $end
$var wire 32 / r1_data [31:0] $end
$var wire 5 0 r1_addr [4:0] $end
$var wire 32 1 fetch_pc [31:0] $end
$var wire 32 2 fetch_ir [31:0] $end
$var wire 1 3 fetch $end
$var wire 1 4 execute $end
$var wire 5 5 decode_rd [4:0] $end
$var wire 7 6 decode_opcode [6:0] $end
$var wire 32 7 decode_op2 [31:0] $end
$var wire 32 8 decode_op1 [31:0] $end
$var wire 13 9 decode_offset [12:0] $end
$var wire 7 : decode_funct7 [6:0] $end
$var wire 3 ; decode_funct3 [2:0] $end
$var wire 1 < decode $end
$var wire 32 = data_in [31:0] $end
$var wire 32 > addr [31:0] $end
$var reg 3 ? next_state [2:0] $end
$var reg 3 @ state [2:0] $end
$scope module instr_decode $end
$var wire 1 < clk $end
$var wire 1 ' rst $end
$var wire 1 A rs2 $end
$var wire 1 B rs1 $end
$var wire 5 C rd [4:0] $end
$var wire 32 D r2_data [31:0] $end
$var wire 32 E r1_data [31:0] $end
$var wire 7 F opcode [6:0] $end
$var wire 32 G ir_in [31:0] $end
$var wire 7 H funct7 [6:0] $end
$var wire 3 I funct3 [2:0] $end
$var reg 32 J ir [31:0] $end
$var reg 13 K offset [12:0] $end
$var reg 32 L op1 [31:0] $end
$var reg 32 M op2 [31:0] $end
$var reg 5 N r1_addr [4:0] $end
$var reg 5 O r2_addr [4:0] $end
$upscope $end
$scope module instr_exec $end
$var wire 1 4 clk $end
$var wire 3 P funct3 [2:0] $end
$var wire 7 Q funct7 [6:0] $end
$var wire 13 R offset [12:0] $end
$var wire 32 S op1 [31:0] $end
$var wire 32 T op2 [31:0] $end
$var wire 7 U opcode [6:0] $end
$var wire 5 V rd [4:0] $end
$var wire 1 ' rst $end
$var wire 32 W pc [31:0] $end
$var reg 32 X mem_addr [31:0] $end
$var reg 1 Y mem_ren $end
$var reg 1 Z mem_wen $end
$var reg 5 [ reg_addr [4:0] $end
$var reg 32 \ reg_data [31:0] $end
$upscope $end
$scope module instr_fetch $end
$var wire 1 3 clk $end
$var wire 32 ] ir [31:0] $end
$var wire 32 ^ pc_data [31:0] $end
$var wire 1 _ pc_set $end
$var wire 1 ' rst $end
$var wire 32 ` mem_data [31:0] $end
$var reg 32 a mem_addr [31:0] $end
$var reg 32 b pc [31:0] $end
$upscope $end
$scope module registers $end
$var wire 1 & clk $end
$var wire 5 c r1_addr [4:0] $end
$var wire 5 d r2_addr [4:0] $end
$var wire 5 e rd1_addr [4:0] $end
$var wire 32 f rd1_data [31:0] $end
$var wire 5 g rd2_addr [4:0] $end
$var wire 32 h rd2_data [31:0] $end
$var wire 1 ' rst $end
$var reg 7 i i [6:0] $end
$var reg 32 j r1_data [31:0] $end
$var reg 32 k r2_data [31:0] $end
$upscope $end
$upscope $end
$scope module mem $end
$var wire 32 l addr [31:0] $end
$var wire 1 & clk $end
$var wire 32 m data_in [31:0] $end
$var wire 1 # mem_ren $end
$var wire 1 " mem_wen $end
$var reg 32 n data_out [31:0] $end
$upscope $end
$upscope $end
$enddefinitions $end
#0
$dumpvars
bx n
b0 m
bx l
bx k
bx j
b100000 i
bz h
bz g
bx f
b0 e
bx d
bx c
b0 b
bx a
bx `
0_
b0 ^
bx ]
bx \
b0 [
xZ
xY
bx X
b0 W
b0 V
b0 U
b0 T
b0 S
b0 R
b0 Q
b0 P
bx O
bx N
b0 M
b0 L
b0 K
b0 J
b0 I
b0 H
bx G
b0 F
bx E
bx D
b0 C
0B
0A
b0 @
b1 ?
bx >
bx =
0<
b0 ;
b0 :
b0 9
b0 8
b0 7
b0 6
b0 5
04
03
bx 2
b0 1
bx 0
bx /
bx .
bx -
b0 ,
bx +
bz *
bz )
b0 (
1'
0&
bx %
bx $
0#
0"
b0 !
$end
#50
b100000 i
1&
#75
0'
#100
0&
#150
b10100000000000010010011 2
b10100000000000010010011 G
b10100000000000010010011 ]
b10100000000000010010011 $
b10100000000000010010011 =
b10100000000000010010011 `
b10100000000000010010011 n
b10 ?
b100 1
b100 W
b100 b
b0 %
b0 >
b0 a
b0 l
1#
13
b1 @
1&
#200
0&
#250
b0 /
b0 E
b0 j
b101 7
b101 M
b101 T
b0 8
b0 L
b0 S
b0 0
b0 N
b0 c
1A
b10011 6
b10011 F
b10011 U
b1 5
b1 C
b1 V
b11 ?
b10100000000000010010011 J
0#
03
1<
b10 @
1&
#300
0&
#350
b1 ?
b101 +
b101 \
b101 f
b1 ,
b1 [
b1 e
0<
14
b11 @
1&
#400
0&
#450
b10000001000000100010011 2
b10000001000000100010011 G
b10000001000000100010011 ]
b10000001000000100010011 $
b10000001000000100010011 =
b10000001000000100010011 `
b10000001000000100010011 n
b10 ?
b1000 1
b1000 W
b1000 b
b100 %
b100 >
b100 a
b100 l
1#
13
04
b1 @
1&
#500
0&
#550
b101 8
b101 L
b101 S
b101 /
b101 E
b101 j
b1 0
b1 N
b1 c
b100 7
b100 M
b100 T
1B
0A
b10 5
b10 C
b10 V
b11 ?
b10000001000000100010011 J
0#
03
1<
b10 @
1&
#600
0&
#650
b1 ?
b1001 +
b1001 \
b1001 f
b10 ,
b10 [
b10 e
0<
14
b11 @
1&
#700
0&
#750
bx 2
bx G
bx ]
bx $
bx =
bx `
bx n
b10 ?
b1100 1
b1100 W
b1100 b
b1000 %
b1000 >
b1000 a
b1000 l
1#
13
04
b1 @
1&
#800
0&
#850
xB
xA
bx 6
bx F
bx U
bx 5
bx C
bx V
bx ;
bx I
bx P
bx :
bx H
bx Q
b11 ?
bx J
0#
03
1<
b10 @
1&
#900
0&
#950
b1 ?
0<
14
b11 @
1&
